pseudb/__init__.py
pseudb/database.py
pseudb/middlewares.py
pseudb/operations.py
pseudb/queries.py
pseudb/storages.py
pseudb/utils.py
pseudb-3.2.1.dist-info/DESCRIPTION.rst
pseudb-3.2.1.dist-info/METADATA
pseudb-3.2.1.dist-info/RECORD
pseudb-3.2.1.dist-info/WHEEL
pseudb-3.2.1.dist-info/metadata.json
pseudb-3.2.1.dist-info/top_level.txt
pseudb-3.2.1.dist-info/zip-safe
tests/__init__.py
tests/conftest.py
tests/test_crud.py
tests/test_middlewares.py
tests/test_operations.py
tests/test_pseudb.py
tests/test_queries.py
tests/test_storages.py
tests/test_tables.py
tests/test_utils.py
