Metadata-Version: 2.0
Name: pseudb
Version: 3.2.1
Summary: PseuDB is inspired by TinyDB and lowdb. It is a tiny, document oriented database optimized for PseuServer and fun :)
Home-page: https://github.com/harryho/pseudb
Author: Harry Ho
Author-email: harry.ho_long@yahoo.com
License: MIT
